cosmoscreen/__init__.py
equiphase-0.0.1.dev1.dist-info/METADATA
equiphase-0.0.1.dev1.dist-info/WHEEL
equiphase-0.0.1.dev1.dist-info/top_level.txt
equiphase-0.0.1.dev1.dist-info/RECORD
